{"status_cd":0,"error_cd":0,"data":{"extra":{"m_shop_items":[{"id":"9322","pic_id":"45119","sort":"1","m_shop_id":"26","name":"★9ピンクの魔石[Legend]","m_item_id_shop":["45119"],"m_item_num_shop":["1"],"m_item_id_money":"3102","m_item_num_money":"250","total_max_count":"0","daily_max_count":"0","weekly_max_count":"0","store_id":"0","text1":"★9ピンクの魔石[Legend]","text2":"個数：1","text3":"","text4":"","m_item_num_money_str":"250","passport_days":0,"shop_item_type":2,"eq_rank":3},{"id":"9323","pic_id":"45219","sort":"2","m_shop_id":"26","name":"★9オレンジの魔石[Legend]","m_item_id_shop":["45219"],"m_item_num_shop":["1"],"m_item_id_money":"3102","m_item_num_money":"250","total_max_count":"0","daily_max_count":"0","weekly_max_count":"0","store_id":"0","text1":"★9オレンジの魔石[Legend]","text2":"個数：1","text3":"","text4":"","m_item_num_money_str":"250","passport_days":0,"shop_item_type":2,"eq_rank":3},{"id":"9324","pic_id":"45319","sort":"3","m_shop_id":"26","name":"★9緑の魔石[Legend]","m_item_id_shop":["45319"],"m_item_num_shop":["1"],"m_item_id_money":"3102","m_item_num_money":"250","total_max_count":"0","daily_max_count":"0","weekly_max_count":"0","store_id":"0","text1":"★9緑の魔石[Legend]","text2":"個数：1","text3":"","text4":"","m_item_num_money_str":"250","passport_days":0,"shop_item_type":2,"eq_rank":3},{"id":"9325","pic_id":"45419","sort":"4","m_shop_id":"26","name":"★9青の魔石[Legend]","m_item_id_shop":["45419"],"m_item_num_shop":["1"],"m_item_id_money":"3102","m_item_num_money":"250","total_max_count":"0","daily_max_count":"0","weekly_max_count":"0","store_id":"0","text1":"★9青の魔石[Legend]","text2":"個数：1","text3":"","text4":"","m_item_num_money_str":"250","passport_days":0,"shop_item_type":2,"eq_rank":3},{"id":"9326","pic_id":"45519","sort":"5","m_shop_id":"26","name":"★9紫の魔石[Legend]","m_item_id_shop":["45519"],"m_item_num_shop":["1"],"m_item_id_money":"3102","m_item_num_money":"250","total_max_count":"0","daily_max_count":"0","weekly_max_count":"0","store_id":"0","text1":"★9紫の魔石[Legend]","text2":"個数：1","text3":"","text4":"","m_item_num_money_str":"250","passport_days":0,"shop_item_type":2,"eq_rank":3},{"id":"9327","pic_id":"45619","sort":"6","m_shop_id":"26","name":"★9赤の魔石[Legend]","m_item_id_shop":["45619"],"m_item_num_shop":["1"],"m_item_id_money":"3102","m_item_num_money":"250","total_max_count":"0","daily_max_count":"0","weekly_max_count":"0","store_id":"0","text1":"★9赤の魔石[Legend]","text2":"個数：1","text3":"","text4":"","m_item_num_money_str":"250","passport_days":0,"shop_item_type":2,"eq_rank":3},{"id":"9328","pic_id":"45719","sort":"7","m_shop_id":"26","name":"★9白の魔石[Legend]","m_item_id_shop":["45719"],"m_item_num_shop":["1"],"m_item_id_money":"3102","m_item_num_money":"250","total_max_count":"0","daily_max_count":"0","weekly_max_count":"0","store_id":"0","text1":"★9白の魔石[Legend]","text2":"個数：1","text3":"","text4":"","m_item_num_money_str":"250","passport_days":0,"shop_item_type":2,"eq_rank":3},{"id":"9315","pic_id":"45118","sort":"11","m_shop_id":"26","name":"★8ピンクの魔石[Legend]","m_item_id_shop":["45118"],"m_item_num_shop":["1"],"m_item_id_money":"3102","m_item_num_money":"100","total_max_count":"0","daily_max_count":"0","weekly_max_count":"0","store_id":"0","text1":"★8ピンクの魔石[Legend]","text2":"個数：1","text3":"","text4":"","m_item_num_money_str":"100","passport_days":0,"shop_item_type":2,"eq_rank":3},{"id":"9316","pic_id":"45218","sort":"12","m_shop_id":"26","name":"★8オレンジの魔石[Legend]","m_item_id_shop":["45218"],"m_item_num_shop":["1"],"m_item_id_money":"3102","m_item_num_money":"100","total_max_count":"0","daily_max_count":"0","weekly_max_count":"0","store_id":"0","text1":"★8オレンジの魔石[Legend]","text2":"個数：1","text3":"","text4":"","m_item_num_money_str":"100","passport_days":0,"shop_item_type":2,"eq_rank":3},{"id":"9317","pic_id":"45318","sort":"13","m_shop_id":"26","name":"★8緑の魔石[Legend]","m_item_id_shop":["45318"],"m_item_num_shop":["1"],"m_item_id_money":"3102","m_item_num_money":"100","total_max_count":"0","daily_max_count":"0","weekly_max_count":"0","store_id":"0","text1":"★8緑の魔石[Legend]","text2":"個数：1","text3":"","text4":"","m_item_num_money_str":"100","passport_days":0,"shop_item_type":2,"eq_rank":3},{"id":"9318","pic_id":"45418","sort":"14","m_shop_id":"26","name":"★8青の魔石[Legend]","m_item_id_shop":["45418"],"m_item_num_shop":["1"],"m_item_id_money":"3102","m_item_num_money":"100","total_max_count":"0","daily_max_count":"0","weekly_max_count":"0","store_id":"0","text1":"★8青の魔石[Legend]","text2":"個数：1","text3":"","text4":"","m_item_num_money_str":"100","passport_days":0,"shop_item_type":2,"eq_rank":3},{"id":"9319","pic_id":"45518","sort":"15","m_shop_id":"26","name":"★8紫の魔石[Legend]","m_item_id_shop":["45518"],"m_item_num_shop":["1"],"m_item_id_money":"3102","m_item_num_money":"100","total_max_count":"0","daily_max_count":"0","weekly_max_count":"0","store_id":"0","text1":"★8紫の魔石[Legend]","text2":"個数：1","text3":"","text4":"","m_item_num_money_str":"100","passport_days":0,"shop_item_type":2,"eq_rank":3},{"id":"9320","pic_id":"45618","sort":"16","m_shop_id":"26","name":"★8赤の魔石[Legend]","m_item_id_shop":["45618"],"m_item_num_shop":["1"],"m_item_id_money":"3102","m_item_num_money":"100","total_max_count":"0","daily_max_count":"0","weekly_max_count":"0","store_id":"0","text1":"★8赤の魔石[Legend]","text2":"個数：1","text3":"","text4":"","m_item_num_money_str":"100","passport_days":0,"shop_item_type":2,"eq_rank":3},{"id":"9321","pic_id":"45718","sort":"17","m_shop_id":"26","name":"★8白の魔石[Legend]","m_item_id_shop":["45718"],"m_item_num_shop":["1"],"m_item_id_money":"3102","m_item_num_money":"100","total_max_count":"0","daily_max_count":"0","weekly_max_count":"0","store_id":"0","text1":"★8白の魔石[Legend]","text2":"個数：1","text3":"","text4":"","m_item_num_money_str":"100","passport_days":0,"shop_item_type":2,"eq_rank":3},{"id":"9302","pic_id":"51","sort":"21","m_shop_id":"26","name":"★7ピンクの魔石[Legend]","m_item_id_shop":["45117"],"m_item_num_shop":["1"],"m_item_id_money":"3102","m_item_num_money":"50","total_max_count":"0","daily_max_count":"0","weekly_max_count":"0","store_id":"0","text1":"★7ピンクの魔石[Legend]","text2":"個数：1","text3":"","text4":"","m_item_num_money_str":"50","passport_days":0,"shop_item_type":2,"eq_rank":3},{"id":"9304","pic_id":"52","sort":"22","m_shop_id":"26","name":"★7オレンジの魔石[Legend]","m_item_id_shop":["45217"],"m_item_num_shop":["1"],"m_item_id_money":"3102","m_item_num_money":"50","total_max_count":"0","daily_max_count":"0","weekly_max_count":"0","store_id":"0","text1":"★7オレンジの魔石[Legend]","text2":"個数：1","text3":"","text4":"","m_item_num_money_str":"50","passport_days":0,"shop_item_type":2,"eq_rank":3},{"id":"9306","pic_id":"53","sort":"23","m_shop_id":"26","name":"★7緑の魔石[Legend]","m_item_id_shop":["45317"],"m_item_num_shop":["1"],"m_item_id_money":"3102","m_item_num_money":"50","total_max_count":"0","daily_max_count":"0","weekly_max_count":"0","store_id":"0","text1":"★7緑の魔石[Legend]","text2":"個数：1","text3":"","text4":"","m_item_num_money_str":"50","passport_days":0,"shop_item_type":2,"eq_rank":3},{"id":"9308","pic_id":"54","sort":"24","m_shop_id":"26","name":"★7青の魔石[Legend]","m_item_id_shop":["45417"],"m_item_num_shop":["1"],"m_item_id_money":"3102","m_item_num_money":"50","total_max_count":"0","daily_max_count":"0","weekly_max_count":"0","store_id":"0","text1":"★7青の魔石[Legend]","text2":"個数：1","text3":"","text4":"","m_item_num_money_str":"50","passport_days":0,"shop_item_type":2,"eq_rank":3},{"id":"9310","pic_id":"55","sort":"25","m_shop_id":"26","name":"★7紫の魔石[Legend]","m_item_id_shop":["45517"],"m_item_num_shop":["1"],"m_item_id_money":"3102","m_item_num_money":"50","total_max_count":"0","daily_max_count":"0","weekly_max_count":"0","store_id":"0","text1":"★7紫の魔石[Legend]","text2":"個数：1","text3":"","text4":"","m_item_num_money_str":"50","passport_days":0,"shop_item_type":2,"eq_rank":3},{"id":"9312","pic_id":"56","sort":"26","m_shop_id":"26","name":"★7赤の魔石[Legend]","m_item_id_shop":["45617"],"m_item_num_shop":["1"],"m_item_id_money":"3102","m_item_num_money":"50","total_max_count":"0","daily_max_count":"0","weekly_max_count":"0","store_id":"0","text1":"★7赤の魔石[Legend]","text2":"個数：1","text3":"","text4":"","m_item_num_money_str":"50","passport_days":0,"shop_item_type":2,"eq_rank":3},{"id":"9314","pic_id":"57","sort":"27","m_shop_id":"26","name":"★7白の魔石[Legend]","m_item_id_shop":["45717"],"m_item_num_shop":["1"],"m_item_id_money":"3102","m_item_num_money":"50","total_max_count":"0","daily_max_count":"0","weekly_max_count":"0","store_id":"0","text1":"★7白の魔石[Legend]","text2":"個数：1","text3":"","text4":"","m_item_num_money_str":"50","passport_days":0,"shop_item_type":2,"eq_rank":3},{"id":"9301","pic_id":"51","sort":"31","m_shop_id":"26","name":"★6ピンクの魔石[Legend]","m_item_id_shop":["45116"],"m_item_num_shop":["1"],"m_item_id_money":"3102","m_item_num_money":"25","total_max_count":"0","daily_max_count":"0","weekly_max_count":"0","store_id":"0","text1":"★6ピンクの魔石[Legend]","text2":"個数：1","text3":"","text4":"","m_item_num_money_str":"25","passport_days":0,"shop_item_type":2,"eq_rank":3},{"id":"9303","pic_id":"52","sort":"32","m_shop_id":"26","name":"★6オレンジの魔石[Legend]","m_item_id_shop":["45216"],"m_item_num_shop":["1"],"m_item_id_money":"3102","m_item_num_money":"25","total_max_count":"0","daily_max_count":"0","weekly_max_count":"0","store_id":"0","text1":"★6オレンジの魔石[Legend]","text2":"個数：1","text3":"","text4":"","m_item_num_money_str":"25","passport_days":0,"shop_item_type":2,"eq_rank":3},{"id":"9305","pic_id":"53","sort":"33","m_shop_id":"26","name":"★6緑の魔石[Legend]","m_item_id_shop":["45316"],"m_item_num_shop":["1"],"m_item_id_money":"3102","m_item_num_money":"25","total_max_count":"0","daily_max_count":"0","weekly_max_count":"0","store_id":"0","text1":"★6緑の魔石[Legend]","text2":"個数：1","text3":"","text4":"","m_item_num_money_str":"25","passport_days":0,"shop_item_type":2,"eq_rank":3},{"id":"9307","pic_id":"54","sort":"34","m_shop_id":"26","name":"★6青の魔石[Legend]","m_item_id_shop":["45416"],"m_item_num_shop":["1"],"m_item_id_money":"3102","m_item_num_money":"25","total_max_count":"0","daily_max_count":"0","weekly_max_count":"0","store_id":"0","text1":"★6青の魔石[Legend]","text2":"個数：1","text3":"","text4":"","m_item_num_money_str":"25","passport_days":0,"shop_item_type":2,"eq_rank":3},{"id":"9309","pic_id":"55","sort":"35","m_shop_id":"26","name":"★6紫の魔石[Legend]","m_item_id_shop":["45516"],"m_item_num_shop":["1"],"m_item_id_money":"3102","m_item_num_money":"25","total_max_count":"0","daily_max_count":"0","weekly_max_count":"0","store_id":"0","text1":"★6紫の魔石[Legend]","text2":"個数：1","text3":"","text4":"","m_item_num_money_str":"25","passport_days":0,"shop_item_type":2,"eq_rank":3},{"id":"9311","pic_id":"56","sort":"36","m_shop_id":"26","name":"★6赤の魔石[Legend]","m_item_id_shop":["45616"],"m_item_num_shop":["1"],"m_item_id_money":"3102","m_item_num_money":"25","total_max_count":"0","daily_max_count":"0","weekly_max_count":"0","store_id":"0","text1":"★6赤の魔石[Legend]","text2":"個数：1","text3":"","text4":"","m_item_num_money_str":"25","passport_days":0,"shop_item_type":2,"eq_rank":3},{"id":"9313","pic_id":"57","sort":"37","m_shop_id":"26","name":"★6白の魔石[Legend]","m_item_id_shop":["45716"],"m_item_num_shop":["1"],"m_item_id_money":"3102","m_item_num_money":"25","total_max_count":"0","daily_max_count":"0","weekly_max_count":"0","store_id":"0","text1":"★6白の魔石[Legend]","text2":"個数：1","text3":"","text4":"","m_item_num_money_str":"25","passport_days":0,"shop_item_type":2,"eq_rank":3}],"campaign_limit":"","present_item":[]}},"timestamp":"1664753008"}